setup.py
pypack/__init__.py
pypack/protocol.py
pypack/pypack.py
pypack/redis_connection.py
pypack2.egg-info/PKG-INFO
pypack2.egg-info/SOURCES.txt
pypack2.egg-info/dependency_links.txt
pypack2.egg-info/requires.txt
pypack2.egg-info/top_level.txt