Metadata-Version: 1.0
Name: pypack2
Version: 0.1
Summary: Python HttpPack server-side plugin based on gevent
Home-page: https://github.com/codemeow5/PyPack
Author: CodeMeow5
Author-email: codemeow@yahoo.com
License: MIT
Keywords: httppack
Platform: UNKNOWN
